[{"date": "Dec. 07, 2025", "games": [{"away_team": "toronto", "home_team": "montr\u00e9al", "venue": "Place Bell | Laval", "type": "regular", "elo_before_home": 1314, "elo_before_away": 1310, "expected_win_home": 0.5770924758253292, "expected_win_away": 0.4229075241746708}, {"away_team": "minnesota", "home_team": "boston", "venue": "Agganis Arena | Boston", "type": "regular", "elo_before_home": 1302, "elo_before_away": 1328, "expected_win_home": 0.5344839447268315, "expected_win_away": 0.4655160552731685}]}, {"date": "Dec. 16, 2025", "games": [{"away_team": "ottawa", "home_team": "vancouver", "venue": "Pacific Coliseum | Vancouver", "type": "regular", "elo_before_home": 1293, "elo_before_away": 1272, "expected_win_home": 0.6007782458900109, "expected_win_away": 0.39922175410998906}]}, {"date": "Dec. 17, 2025", "games": [{"away_team": "boston", "home_team": "new_york", "venue": "Prudential Center | Newark", "type": "regular", "elo_before_home": 1286, "elo_before_away": 1302, "expected_win_home": 0.5487743358597418, "expected_win_away": 0.4512256641402582}, {"away_team": "ottawa", "home_team": "seattle", "venue": "Climate Pledge Arena | Seattle", "type": "regular", "elo_before_home": 1295, "elo_before_away": 1272, "expected_win_home": 0.603536318526178, "expected_win_away": 0.39646368147382205}]}]