[{"date": "Dec. 04, 2025", "games": [{"away_team": "ottawa", "home_team": "toronto", "venue": "Coca-Cola Coliseum | Toronto", "type": "regular", "elo_before_home": 1307, "elo_before_away": 1275, "expected_win_home": 0.615864104253756, "expected_win_away": 0.38413589574624396}]}, {"date": "Dec. 06, 2025", "games": [{"away_team": "new_york", "home_team": "vancouver", "venue": "Pacific Coliseum | Vancouver", "type": "regular", "elo_before_home": 1289, "elo_before_away": 1290, "expected_win_home": 0.5700528235839882, "expected_win_away": 0.42994717641601177}]}, {"date": "Dec. 07, 2025", "games": [{"away_team": "toronto", "home_team": "montr\u00e9al", "venue": "Place Bell | Laval", "type": "regular", "elo_before_home": 1314, "elo_before_away": 1307, "expected_win_home": 0.581301478368915, "expected_win_away": 0.418698521631085}, {"away_team": "minnesota", "home_team": "boston", "venue": "Agganis Arena | Boston", "type": "regular", "elo_before_home": 1302, "elo_before_away": 1328, "expected_win_home": 0.5344839447268315, "expected_win_away": 0.4655160552731685}]}, {"date": "Dec. 16, 2025", "games": [{"away_team": "ottawa", "home_team": "vancouver", "venue": "Pacific Coliseum | Vancouver", "type": "regular", "elo_before_home": 1289, "elo_before_away": 1275, "expected_win_home": 0.5910755963149434, "expected_win_away": 0.40892440368505656}]}]